whey_conda/__init__.py
whey_conda/config.py
whey_conda/py.typed
whey_conda-0.3.0.dist-info/LICENSE
whey_conda-0.3.0.dist-info/METADATA
whey_conda-0.3.0.dist-info/WHEEL
whey_conda-0.3.0.dist-info/entry_points.txt
whey_conda-0.3.0.dist-info/RECORD
